{
    "BMR": {
        "C14": {
            "ft0k": 8,
            "fc0k": 16,
            "e005": 4.7
        },
        "C16": {
            "ft0k": 10,
            "fc0k": 17,
            "e005": 5.4
        },
        "C18": {
            "ft0k": 11,
            "fc0k": 18,
            "e005": 6.0
        },
        "C20": {
            "ft0k": 12,
            "fc0k": 19,
            "e005": 6.4
        },
        "C22": {
            "ft0k": 13,
            "fc0k": 20,
            "e005": 6.7
        },
        "C24": {
            "ft0k": 14,
            "fc0k": 21,
            "e005": 7.4
        },
        "C27": {
            "ft0k": 16,
            "fc0k": 22,
            "e005": 7.7
        },
        "C30": {
            "ft0k": 18,
            "fc0k": 23,
            "e005": 8.0
        },
        "C35": {
            "ft0k": 21,
            "fc0k": 25,
            "e005": 8.7
        },
        "C40": {
            "ft0k": 24,
            "fc0k": 26,
            "e005": 9.4
        },
        "C45": {
            "ft0k": 27,
            "fc0k": 27,
            "e005": 10.0
        },
        "C50": {
            "ft0k": 30,
            "fc0k": 29,
            "e005": 10.7
        }
    },
    "BMF": {
        "D18": {
            "ft0k": 11,
            "fc0k": 18,
            "e005": 8
        },
        "D24": {
            "ft0k": 14,
            "fc0k": 21,
            "e005": 8.5
        },
        "D30": {
            "ft0k": 18,
            "fc0k": 23,
            "e005": 9.2
        },
        "D35": {
            "ft0k": 21,
            "fc0k": 25,
            "e005": 10.1
        },
        "D40": {
            "ft0k": 24,
            "fc0k": 26,
            "e005": 10.9
        },
        "D50": {
            "ft0k": 30,
            "fc0k": 29,
            "e005": 11.8
        },
        "D60": {
            "ft0k": 36,
            "fc0k": 32,
            "e005": 14.3
        },
        "D70": {
            "ft0k": 42,
            "fc0k": 34,
            "e005": 16.8
        }
    },
    "BLC": {
        "GL24h": {
            "ft0k": 16.5,
            "fc0k": 24,
            "e005": 9.4
        },
        "GL28h": {
            "ft0k": 19.5,
            "fc0k": 26.5,
            "e005": 10.2
        },
        "GL32h": {
            "ft0k": 22.5,
            "fc0k": 29,
            "e005": 11.1
        },
        "GL36h": {
            "ft0k": 26.0,
            "fc0k": 31,
            "e005": 11.9
        },
        "GL24c": {
            "ft0k": 14,
            "fc0k": 21,
            "e005": 9.4
        },
        "GL28c": {
            "ft0k": 16.5,
            "fc0k": 24,
            "e005": 10.2
        },
        "GL32c": {
            "ft0k": 19.5,
            "fc0k": 26.5,
            "e005": 11.1
        },
        "GL36c": {
            "ft0k": 22.5,
            "fc0k": 29,
            "e005": 11.9
        }
    }
}
